[{"customLabel":true,"detailHeading":true,"editHeading":true,"label":"Information","layoutColumns":[{"layoutItems":[{"analyticsCloudComponent":null,"behavior":"Required","canvas":null,"component":null,"customLink":null,"emptySpace":null,"field":"compliancequest__Step__c","height":null,"page":null,"reportChartComponent":null,"scontrol":null,"showLabel":null,"showScrollbars":null,"width":null},{"analyticsCloudComponent":null,"behavior":"Required","canvas":null,"component":null,"customLink":null,"emptySpace":null,"field":"compliancequest__SQX_Parent__c","height":null,"page":null,"reportChartComponent":null,"scontrol":null,"showLabel":null,"showScrollbars":null,"width":null},{"analyticsCloudComponent":null,"behavior":"Readonly","canvas":null,"component":null,"customLink":null,"emptySpace":null,"field":"compliancequest__SQX_Change_Order__c","height":null,"page":null,"reportChartComponent":null,"scontrol":null,"showLabel":null,"showScrollbars":null,"width":null},{"analyticsCloudComponent":null,"behavior":"Readonly","canvas":null,"component":null,"customLink":null,"emptySpace":null,"field":"compliancequest__Title__c","height":null,"page":null,"reportChartComponent":null,"scontrol":null,"showLabel":null,"showScrollbars":null,"width":null},{"analyticsCloudComponent":null,"behavior":"Edit","canvas":null,"component":null,"customLink":null,"emptySpace":null,"field":"compliancequest__Due_Date__c","height":null,"page":null,"reportChartComponent":null,"scontrol":null,"showLabel":null,"showScrollbars":null,"width":null}],"reserved":null},{"layoutItems":[{"analyticsCloudComponent":null,"behavior":"Readonly","canvas":null,"component":null,"customLink":null,"emptySpace":null,"field":"compliancequest__Type__c","height":null,"page":null,"reportChartComponent":null,"scontrol":null,"showLabel":null,"showScrollbars":null,"width":null},{"analyticsCloudComponent":null,"behavior":"Readonly","canvas":null,"component":null,"customLink":null,"emptySpace":null,"field":"compliancequest__Description__c","height":null,"page":null,"reportChartComponent":null,"scontrol":null,"showLabel":null,"showScrollbars":null,"width":null},{"analyticsCloudComponent":null,"behavior":"Edit","canvas":null,"component":null,"customLink":null,"emptySpace":null,"field":"compliancequest__SQX_User__c","height":null,"page":null,"reportChartComponent":null,"scontrol":null,"showLabel":null,"showScrollbars":null,"width":null}],"reserved":null}],"style":"TwoColumnsLeftToRight"},{"customLabel":true,"detailHeading":true,"editHeading":true,"label":"Controlled Document","layoutColumns":[{"layoutItems":[{"analyticsCloudComponent":null,"behavior":"Readonly","canvas":null,"component":null,"customLink":null,"emptySpace":null,"field":"compliancequest__SQX_Controlled_Document__c","height":null,"page":null,"reportChartComponent":null,"scontrol":null,"showLabel":null,"showScrollbars":null,"width":null},{"analyticsCloudComponent":null,"behavior":"Readonly","canvas":null,"component":null,"customLink":null,"emptySpace":null,"field":"compliancequest__Controlled_Document_Status__c","height":null,"page":null,"reportChartComponent":null,"scontrol":null,"showLabel":null,"showScrollbars":null,"width":null}],"reserved":null},{"layoutItems":[{"analyticsCloudComponent":null,"behavior":"Edit","canvas":null,"component":null,"customLink":null,"emptySpace":null,"field":"compliancequest__SQX_Controlled_Document_New__c","height":null,"page":null,"reportChartComponent":null,"scontrol":null,"showLabel":null,"showScrollbars":null,"width":null}],"reserved":null}],"style":"TwoColumnsLeftToRight"},{"customLabel":true,"detailHeading":true,"editHeading":true,"label":"SignOff","layoutColumns":[{"layoutItems":[{"analyticsCloudComponent":null,"behavior":"Required","canvas":null,"component":null,"customLink":null,"emptySpace":null,"field":"compliancequest__Status__c","height":null,"page":null,"reportChartComponent":null,"scontrol":null,"showLabel":null,"showScrollbars":null,"width":null},{"analyticsCloudComponent":null,"behavior":"Edit","canvas":null,"component":null,"customLink":null,"emptySpace":null,"field":"compliancequest__Completed_By__c","height":null,"page":null,"reportChartComponent":null,"scontrol":null,"showLabel":null,"showScrollbars":null,"width":null}],"reserved":null},{"layoutItems":[{"analyticsCloudComponent":null,"behavior":"Edit","canvas":null,"component":null,"customLink":null,"emptySpace":null,"field":"compliancequest__Completion_Date__c","height":null,"page":null,"reportChartComponent":null,"scontrol":null,"showLabel":null,"showScrollbars":null,"width":null},{"analyticsCloudComponent":null,"behavior":"Edit","canvas":null,"component":null,"customLink":null,"emptySpace":null,"field":"compliancequest__Remark__c","height":null,"page":null,"reportChartComponent":null,"scontrol":null,"showLabel":null,"showScrollbars":null,"width":null}],"reserved":null}],"style":"TwoColumnsLeftToRight"}]